loom_mcp/__init__.py
loom_mcp/server.py
loom_mcp/clients/__init__.py
loom_mcp/clients/loom.py
loom_mcp/tools/__init__.py
loom_mcp/tools/edit_video.py
loom_mcp/tools/get_video.py
loom_mcp/tools/list_recorded_videos.py
loom_mcp/tools/merge_videos.py
m2ai_mcp_loom_advisor-1.0.0.dist-info/METADATA
m2ai_mcp_loom_advisor-1.0.0.dist-info/WHEEL
m2ai_mcp_loom_advisor-1.0.0.dist-info/entry_points.txt
m2ai_mcp_loom_advisor-1.0.0.dist-info/licenses/LICENSE
m2ai_mcp_loom_advisor-1.0.0.dist-info/RECORD
